setup.cfg
setup.py
swgoh_api/__init__.py
swgoh_api/swgoh_api.py
swgoh_api.egg-info/PKG-INFO
swgoh_api.egg-info/SOURCES.txt
swgoh_api.egg-info/dependency_links.txt
swgoh_api.egg-info/not-zip-safe
swgoh_api.egg-info/requires.txt
swgoh_api.egg-info/top_level.txt
swgoh_api/entities/__init__.py
swgoh_api/entities/guild.py
swgoh_api/entities/player.py
swgoh_api/entities/requirement.py
swgoh_api/entities/unit.py
swgoh_api/loaders/__init__.py
swgoh_api/loaders/base_loader.py
swgoh_api/loaders/base_local_loader.py
swgoh_api/loaders/base_remote_loader.py
swgoh_api/loaders/guild_loader.py
swgoh_api/loaders/image_loader.py
swgoh_api/loaders/player_loader.py
swgoh_api/loaders/unit_loader.py
swgoh_api/url_requests/__init__.py
swgoh_api/url_requests/requester.py
swgoh_api/url_requests/url_request.py
swgoh_api/utils/__init__.py
swgoh_api/utils/image.py
swgoh_api/utils/singleton.py