Metadata-Version: 2.1
Name: swgoh-api
Version: 1.0.3
Summary: Library for getting info about Guilds, Players, Units and e.t.c from https://swgoh.gg
Author: PackledD
Author-email: da9ert0n@gmail.com
